license.txt
setup.py
extended_parker_oldenburg/__init__.py
extended_parker_oldenburg/crust.py
extended_parker_oldenburg/distance.py
extended_parker_oldenburg/example_forward.py
extended_parker_oldenburg/example_inverse.py
extended_parker_oldenburg/global_grav_1min.py
extended_parker_oldenburg/interfacetovgg.py
extended_parker_oldenburg/plt_tools.py
extended_parker_oldenburg/vggtointerface.py
extended_parker_oldenburg.egg-info/PKG-INFO
extended_parker_oldenburg.egg-info/SOURCES.txt
extended_parker_oldenburg.egg-info/dependency_links.txt
extended_parker_oldenburg.egg-info/requires.txt
extended_parker_oldenburg.egg-info/top_level.txt
extended_parker_oldenburg/dataset/crust1.bnds
extended_parker_oldenburg/dataset/crust1.rho